LICENSE.txt
MANIFEST.in
README.txt
setup.py
pcart_init/__init__.py
pcart_init.egg-info/PKG-INFO
pcart_init.egg-info/SOURCES.txt
pcart_init.egg-info/dependency_links.txt
pcart_init.egg-info/not-zip-safe
pcart_init.egg-info/requires.txt
pcart_init.egg-info/top_level.txt
pcart_init/management/__init__.py
pcart_init/management/commands/__init__.py
pcart_init/management/commands/init_shop.py
pcart_init/management/commands/init_tires_shop.py